gimad/__init__.py
gimad/_commands/__init__.py
gimad/_commands/down.py
gimad/_commands/init.py
gimad/_commands/new.py
gimad/_commands/redo.py
gimad/_commands/up.py
gimad/_config.py
gimad/_db.py
gimad/_runner.py
gimad/_template.py
gimad/_utils.py
postgres_migration-0.1.0.dist-info/METADATA
postgres_migration-0.1.0.dist-info/WHEEL
postgres_migration-0.1.0.dist-info/entry_points.txt
postgres_migration-0.1.0.dist-info/licenses/LICENSE
postgres_migration-0.1.0.dist-info/RECORD
