Metadata-Version: 2.1
Name: postgres-migration
Version: 0.1.0
Summary: Non-schema database migration tool for PostgreSQL
Author-Email: PTNGlobal <support@ptnglobalcorp.com>
License:                                  Apache License
Project-URL: Source, https://github.com/ptnglobalcorp/postgres-migrate
Requires-Python: >=3.12
Requires-Dist: psycopg[binary]
Requires-Dist: typer
Requires-Dist: pydantic-settings
